.gitignore
.gitmodules
.nojekyll
Makefile
README.md
__init__.py
index.html
setup.py
sikuliserver.bat
sikuliserver.sh
docs/Running_The_Server.rst
docs/SikuliServer.rst
docs/Using_From_RobotFramework.rst
docs/conf.py
docs/index.rst
docs/jython_sikuli_server.classes.rst
docs/jython_sikuli_server.robotremoteserver.rst
docs/jython_sikuli_server.rst
docs/jython_sikuli_server.sikuli_class.rst
docs/make.bat
docs/regen.py
src/jython_sikuli_server/__init__.py
src/jython_sikuli_server/classes.py
src/jython_sikuli_server/robotremoteserver.py
src/jython_sikuli_server/sikuli_class.py
src/jython_sikuli_server/version
src/jython_sikuli_server.egg-info/PKG-INFO
src/jython_sikuli_server.egg-info/SOURCES.txt
src/jython_sikuli_server.egg-info/dependency_links.txt
src/jython_sikuli_server.egg-info/top_level.txt