Metadata-Version: 1.1
Name: jython-sikuli-server
Version: 0.1.8.2
Summary: Jython script to run a robot remote library exposing the Sikuli API (and popen).
Home-page: https://github.com/alistair-broomhead/jython-sikuli-server
Author: Alistair Broomhead
Author-email: alistair.broomhead@gmail.com
License: MIT
Download-URL: https://github.com/alistair-broomhead/jython-sikuli-server/zipball/master
Platform: UNKNOWN
